myarithmetic.py
setup.py
myarithmetic.egg-info/PKG-INFO
myarithmetic.egg-info/SOURCES.txt
myarithmetic.egg-info/dependency_links.txt
myarithmetic.egg-info/entry_points.txt
myarithmetic.egg-info/top_level.txt
myarithmetic.egg-info/zip-safe