Metadata-Version: 1.0
Name: myarithmetic
Version: 1.0.1
Summary: myarithmetic
Home-page: http://pypi.python.org/pypi/myarithmetic
Author: coolsnow77
Author-email: cuimingwen001@126.com
License: Apache
Keywords: myarithmetic
Platform: UNKNOWN
